imap_detach/imap_client.py
imap_detach/utils.py
imap_detach/pool.py
imap_detach/cmd.py
imap_detach/expressions.py
imap_detach/__init__.py
imap_detach/mail_info.py
imap_detach/download.py
imap_detach/filter.py
imap_detach-0.4.11.data/scripts/detach.py
imap_detach-0.4.11.dist-info/RECORD
imap_detach-0.4.11.dist-info/METADATA
imap_detach-0.4.11.dist-info/top_level.txt
imap_detach-0.4.11.dist-info/DESCRIPTION.rst
imap_detach-0.4.11.dist-info/WHEEL
imap_detach-0.4.11.dist-info/metadata.json
