Metadata-Version: 2.0
Name: imap-detach
Version: 0.4.11
Summary: A tool to automatically download attachments from IMAP mailbox
Home-page: http://zderadicka.eu/projects/python/imap_detach-tool-download-email-attachments/
Author: Ivan Zderadicka
Author-email: ivan.zderadicka@gmail.com
License: GPL v3
Keywords: email,IMAP,attachment
Platform: UNKNOWN
Classifier: Development Status :: 4 - Beta
Classifier: Environment :: Console
Classifier: License :: OSI Approved :: GNU General Public License v3 (GPLv3)
Classifier: Natural Language :: English
Classifier: Operating System :: POSIX
Classifier: Programming Language :: Python :: 2.7
Classifier: Programming Language :: Python :: 3.4
Classifier: Topic :: Communications :: Email
Provides: imap_detach
Requires-Dist: six (>=1.10.0)
Requires-Dist: imapclient (==1.0.0)
Requires-Dist: parsimonious (>=0.6.2)
